SecretSharer/Compute_Exposure.py
SecretSharer/Compute_Perplexity.py
SecretSharer/Generate_Canaries.py
SecretSharer/__init__.py
tests/__init__.py
tests/test_compute_exposure.py
tests/test_compute_perplexity.py
tests/test_generate_canaries.py
SecretSharer-0.1.0.dist-info/LICENSE.txt
SecretSharer-0.1.0.dist-info/METADATA
SecretSharer-0.1.0.dist-info/WHEEL
SecretSharer-0.1.0.dist-info/entry_points.txt
SecretSharer-0.1.0.dist-info/top_level.txt
SecretSharer-0.1.0.dist-info/RECORD
